geneticalgorithm/__init__.py
geneticalgorithm/geneticalgorithm.py
geneticalgorithm-1.0.0.dist-info/LICENSE
geneticalgorithm-1.0.0.dist-info/METADATA
geneticalgorithm-1.0.0.dist-info/WHEEL
geneticalgorithm-1.0.0.dist-info/top_level.txt
geneticalgorithm-1.0.0.dist-info/RECORD
