Metadata-Version: 2.1
Name: geneticalgorithm
Version: 1.0.0
Summary: An easy implementation of genetic-algorithm (GA) to solve continuous and combinatorial optimization problems with real, integer, and mixed variables in Python
Home-page: https://github.com/rmsolgi/geneticalgorithm
Author: Ryan (Mohammad) Solgi
Author-email: ryan.solgi@gmail.com
Maintainer: Ryan (Mohammad) Solgi
License: UNKNOWN
Keywords: solve,optimization,problem,genetic,algorithm,GA,easy,fast,genetic-algorithm,combinatorial,mixed,evolutionary
Platform: UNKNOWN
Classifier: Programming Language :: Python :: 3
Classifier: License :: OSI Approved :: MIT License
Classifier: Operating System :: OS Independent
Classifier: Topic :: Software Development :: Libraries :: Python Modules
